barf/__init__.py
barf/barf.py
barf/analysis/__init__.py
barf/analysis/codeanalyzer/__init__.py
barf/analysis/codeanalyzer/codeanalyzer.py
barf/analysis/gadgets/__init__.py
barf/analysis/gadgets/classifier.py
barf/analysis/gadgets/finder.py
barf/analysis/gadgets/gadget.py
barf/analysis/gadgets/verifier.py
barf/analysis/graphs/__init__.py
barf/analysis/graphs/basicblock.py
barf/analysis/graphs/callgraph.py
barf/analysis/graphs/controlflowgraph.py
barf/analysis/symbolic/__init__.py
barf/analysis/symbolic/emulator.py
barf/arch/__init__.py
barf/arch/arch.py
barf/arch/disassembler.py
barf/arch/emulator.py
barf/arch/helper.py
barf/arch/translator.py
barf/arch/arm/__init__.py
barf/arch/arm/arm.py
barf/arch/arm/disassembler.py
barf/arch/arm/helpers.py
barf/arch/arm/parser.py
barf/arch/arm/translator.py
barf/arch/arm/translators/__init__.py
barf/arch/arm/translators/branch.py
barf/arch/arm/translators/data.py
barf/arch/arm/translators/loadstore.py
barf/arch/x86/__init__.py
barf/arch/x86/disassembler.py
barf/arch/x86/helpers.py
barf/arch/x86/parser.py
barf/arch/x86/trace.py
barf/arch/x86/translator.py
barf/arch/x86/x86.py
barf/arch/x86/translators/__init__.py
barf/arch/x86/translators/arithmetic.py
barf/arch/x86/translators/bitwise.py
barf/arch/x86/translators/control.py
barf/arch/x86/translators/flag.py
barf/arch/x86/translators/helpers.py
barf/arch/x86/translators/logical.py
barf/arch/x86/translators/misc.py
barf/arch/x86/translators/sse.py
barf/arch/x86/translators/string.py
barf/arch/x86/translators/transfer.py
barf/core/__init__.py
barf/core/binary.py
barf/core/symbols.py
barf/core/reil/__init__.py
barf/core/reil/builder.py
barf/core/reil/container.py
barf/core/reil/helpers.py
barf/core/reil/parser.py
barf/core/reil/reil.py
barf/core/reil/emulator/__init__.py
barf/core/reil/emulator/cpu.py
barf/core/reil/emulator/emulator.py
barf/core/reil/emulator/memory.py
barf/core/reil/emulator/tainter.py
barf/core/smt/__init__.py
barf/core/smt/smtfunction.py
barf-0.6.0.dist-info/LICENSE
barf-0.6.0.dist-info/METADATA
barf-0.6.0.dist-info/WHEEL
barf-0.6.0.dist-info/entry_points.txt
barf-0.6.0.dist-info/top_level.txt
barf-0.6.0.dist-info/RECORD
